{
  "id": "ent.puppet.x-b99813b0",
  "type": "puppet",
  "name": "元婴期傀儡",
  "aliases": [
    "藤家傀儡"
  ],
  "summary": "得自藤家核心族人之一的元婴期傀儡；本章两具助战，一具被藤一击碎、一具存留并自行修复。",
  "attributes": {
    "操控者": "王林",
    "品阶": "元婴期",
    "本体来源": "藤家核心族人"
  },
  "observations": {
    "操控者": [
      {
        "value": "王林",
        "docId": "plot.xianni-ch242-punanzi",
        "seq": 226
      }
    ],
    "品阶": [
      {
        "value": "元婴期",
        "docId": "plot.xianni-ch242-punanzi",
        "seq": 226
      }
    ],
    "本体来源": [
      {
        "value": "藤家核心族人",
        "docId": "plot.xianni-ch242-punanzi",
        "seq": 226
      }
    ]
  },
  "firstSeq": 226,
  "attrProvenance": {
    "操控者": {
      "asOf": null,
      "docId": "plot.xianni-ch242-punanzi",
      "dated": false,
      "seq": 226
    },
    "品阶": {
      "asOf": null,
      "docId": "plot.xianni-ch242-punanzi",
      "dated": false,
      "seq": 226
    },
    "本体来源": {
      "asOf": null,
      "docId": "plot.xianni-ch242-punanzi",
      "dated": false,
      "seq": 226
    }
  },
  "contested": false,
  "contradictions": {},
  "docs": [
    "plot.xianni-ch242-punanzi"
  ],
  "updatedAt": "2026-07-23T04:56:01.414Z"
}
