{
  "id": "ent.beast.x-a67e15c1",
  "type": "beast",
  "name": "离天蟾蜍",
  "aliases": [
    "离天"
  ],
  "summary": "孟驼子肩上的蟾蜍灵兽，可作替身但代价必死，本片段被收回未用。",
  "attributes": {
    "主人": "孟驼子",
    "能力": "可作替身（用之必死）",
    "等级": "上品巅峰灵兽（次荒级）",
    "外形": "蟾蜍，背部鼓包流恶臭黑液"
  },
  "observations": {
    "主人": [
      {
        "value": "孟驼子",
        "docId": "plot.xianni-ch173-second-demon-head",
        "seq": 158
      }
    ],
    "能力": [
      {
        "value": "可作替身（用之必死）",
        "docId": "plot.xianni-ch173-second-demon-head",
        "seq": 158
      }
    ],
    "等级": [
      {
        "value": "上品巅峰灵兽（次荒级）",
        "docId": "plot.xianni-ch173-second-demon-head",
        "seq": 158
      }
    ],
    "外形": [
      {
        "value": "蟾蜍，背部鼓包流恶臭黑液",
        "docId": "plot.xianni-ch173-second-demon-head",
        "seq": 158
      }
    ]
  },
  "firstSeq": 158,
  "attrProvenance": {
    "主人": {
      "asOf": null,
      "docId": "plot.xianni-ch173-second-demon-head",
      "dated": false,
      "seq": 158
    },
    "能力": {
      "asOf": null,
      "docId": "plot.xianni-ch173-second-demon-head",
      "dated": false,
      "seq": 158
    },
    "等级": {
      "asOf": null,
      "docId": "plot.xianni-ch173-second-demon-head",
      "dated": false,
      "seq": 158
    },
    "外形": {
      "asOf": null,
      "docId": "plot.xianni-ch173-second-demon-head",
      "dated": false,
      "seq": 158
    }
  },
  "contested": false,
  "contradictions": {},
  "docs": [
    "plot.xianni-ch173-second-demon-head"
  ],
  "updatedAt": "2026-07-06T16:27:55.067Z"
}
