{
  "id": "ent.person.x-2f268028",
  "type": "person",
  "name": "秦古雷",
  "aliases": [
    "秦古雷老者"
  ],
  "summary": "玄道宗三长老之一，反驳道虚媚术之说，称两名弟子为天生单一水灵根。",
  "attributes": {
    "身份": "玄道宗长辈",
    "阵营": "玄道宗"
  },
  "observations": {
    "身份": [
      {
        "value": "玄道宗长辈",
        "docId": "plot.xianni-ch37-42-sinian-guangban",
        "seq": 37
      }
    ],
    "阵营": [
      {
        "value": "玄道宗",
        "docId": "plot.xianni-ch37-42-sinian-guangban",
        "seq": 37
      }
    ]
  },
  "firstSeq": 37,
  "attrProvenance": {
    "身份": {
      "asOf": null,
      "docId": "plot.xianni-ch37-42-sinian-guangban",
      "dated": false,
      "seq": 37
    },
    "阵营": {
      "asOf": null,
      "docId": "plot.xianni-ch37-42-sinian-guangban",
      "dated": false,
      "seq": 37
    }
  },
  "contested": false,
  "contradictions": {},
  "docs": [
    "plot.xianni-ch37-42-sinian-guangban"
  ],
  "updatedAt": "2026-06-22T12:17:36.025Z"
}
