{
  "id": "ent.person.x-76bccd6c",
  "type": "person",
  "name": "玄道宗马姓老者",
  "aliases": [
    "马师兄",
    "马姓老者"
  ],
  "summary": "玄道宗集结地的筑基中期老者，出言不逊放飓风攻王林，被王林一剑冻杀。",
  "attributes": {
    "小阶段": "筑基中期",
    "身份": "玄道宗弟子",
    "存殁": "死亡",
    "死因": "被王林绿色飞剑一剑冻杀，胸口现碗大伤口气绝",
    "结局": "本章身亡"
  },
  "observations": {
    "小阶段": [
      {
        "value": "筑基中期",
        "docId": "lore.xianni-ch105-jijing-realm",
        "seq": 90
      }
    ],
    "身份": [
      {
        "value": "玄道宗弟子",
        "docId": "lore.xianni-ch105-jijing-realm",
        "seq": 90
      }
    ],
    "存殁": [
      {
        "value": "死亡",
        "docId": "lore.xianni-ch105-jijing-realm",
        "seq": 90
      }
    ],
    "死因": [
      {
        "value": "被王林绿色飞剑一剑冻杀，胸口现碗大伤口气绝",
        "docId": "lore.xianni-ch105-jijing-realm",
        "seq": 90
      }
    ],
    "结局": [
      {
        "value": "本章身亡",
        "docId": "lore.xianni-ch105-jijing-realm",
        "seq": 90
      }
    ]
  },
  "firstSeq": 90,
  "attrProvenance": {
    "小阶段": {
      "asOf": null,
      "docId": "lore.xianni-ch105-jijing-realm",
      "dated": false,
      "seq": 90
    },
    "身份": {
      "asOf": null,
      "docId": "lore.xianni-ch105-jijing-realm",
      "dated": false,
      "seq": 90
    },
    "存殁": {
      "asOf": null,
      "docId": "lore.xianni-ch105-jijing-realm",
      "dated": false,
      "seq": 90
    },
    "死因": {
      "asOf": null,
      "docId": "lore.xianni-ch105-jijing-realm",
      "dated": false,
      "seq": 90
    },
    "结局": {
      "asOf": null,
      "docId": "lore.xianni-ch105-jijing-realm",
      "dated": false,
      "seq": 90
    }
  },
  "contested": false,
  "contradictions": {},
  "docs": [
    "lore.xianni-ch105-jijing-realm"
  ],
  "updatedAt": "2026-07-05T03:14:59.663Z"
}
