{
  "id": "ent.person.x-aca98c34",
  "type": "person",
  "name": "赵传良",
  "aliases": [
    "尸阴宗宗主赵传良"
  ],
  "summary": "尸阴宗当代宗主，被上宗限十日追查4876夺舍失踪案，体内寄有夜自在。",
  "attributes": {
    "身份": "尸阴宗当代宗主、尸阴宗统领者、尸阴宗元婴修士",
    "阵营": "尸阴宗",
    "标志特征": "体内寄魂夜自在",
    "小阶段": "元婴初期"
  },
  "observations": {
    "身份": [
      {
        "value": "尸阴宗当代宗主",
        "docId": "plot.xianni-ch147-150-shendaoshu-deal",
        "seq": 147
      },
      {
        "value": "尸阴宗统领者",
        "docId": "plot.xianni-ch147-150-shendaoshu-deal",
        "seq": 147
      },
      {
        "value": "尸阴宗元婴修士",
        "docId": "plot.xianni-ch147-150-shendaoshu-deal",
        "seq": 147
      }
    ],
    "阵营": [
      {
        "value": "尸阴宗",
        "docId": "plot.xianni-ch147-150-shendaoshu-deal",
        "seq": 147
      }
    ],
    "标志特征": [
      {
        "value": "体内寄魂夜自在",
        "docId": "plot.xianni-ch147-150-shendaoshu-deal",
        "seq": 147
      }
    ],
    "小阶段": [
      {
        "value": "元婴初期",
        "docId": "plot.xianni-ch147-150-shendaoshu-deal",
        "seq": 147
      }
    ]
  },
  "firstSeq": 147,
  "attrProvenance": {
    "身份": {
      "asOf": null,
      "docId": "plot.xianni-ch147-150-shendaoshu-deal",
      "dated": false,
      "seq": 147
    },
    "阵营": {
      "asOf": null,
      "docId": "plot.xianni-ch147-150-shendaoshu-deal",
      "dated": false,
      "seq": 147
    },
    "标志特征": {
      "asOf": null,
      "docId": "plot.xianni-ch147-150-shendaoshu-deal",
      "dated": false,
      "seq": 147
    },
    "小阶段": {
      "asOf": null,
      "docId": "plot.xianni-ch147-150-shendaoshu-deal",
      "dated": false,
      "seq": 147
    }
  },
  "contested": false,
  "contradictions": {},
  "docs": [
    "plot.xianni-ch147-150-shendaoshu-deal"
  ],
  "updatedAt": "2026-07-06T15:33:53.321Z"
}
