{
  "id": "ent.person.x-afce7db5",
  "type": "person",
  "name": "张狂",
  "aliases": [
    "二师兄",
    "紫衣男子",
    "紫衣二师兄",
    "紫衣青年",
    "二师兄张狂"
  ],
  "summary": "恒岳派二师兄，去年比试最强者；本章以紫衣冷峻形象现身交易会，气息远超孙大柱与张虎，以凝气4-9层口诀换走王林灵气泉水。",
  "attributes": {
    "身份": "恒岳派内门弟子、恒岳派后山主事二师兄、恒岳派内门弟子（师兄）",
    "称号": "二师兄",
    "小阶段": "凝气第六层、凝气期第六层",
    "外貌": "约二十岁、紫衣、神态冰冷、紫衣青年、冷峻",
    "标志特征": "气息极危险，远超孙大柱、张虎",
    "性格": "心机深沉、伪作亲和"
  },
  "observations": {
    "身份": [
      {
        "value": "恒岳派内门弟子",
        "docId": "plot.xianni-ch31-36-xueshui-jiaoyi",
        "seq": 31
      },
      {
        "value": "恒岳派后山主事二师兄",
        "docId": "plot.xianni-ch31-36-xueshui-jiaoyi",
        "seq": 31
      },
      {
        "value": "恒岳派内门弟子（师兄）",
        "docId": "plot.xianni-ch37-42-sinian-guangban",
        "seq": 37
      }
    ],
    "称号": [
      {
        "value": "二师兄",
        "docId": "plot.xianni-ch31-36-xueshui-jiaoyi",
        "seq": 31
      }
    ],
    "小阶段": [
      {
        "value": "凝气第六层",
        "docId": "plot.xianni-ch31-36-xueshui-jiaoyi",
        "seq": 31,
        "note": "据弟子所述去年比试最强；本章现身气息远超寻常弟子，疑深藏修为"
      },
      {
        "value": "凝气期第六层",
        "docId": "plot.xianni-ch31-36-xueshui-jiaoyi",
        "seq": 31
      }
    ],
    "外貌": [
      {
        "value": "约二十岁、紫衣、神态冰冷",
        "docId": "plot.xianni-ch31-36-xueshui-jiaoyi",
        "seq": 31
      },
      {
        "value": "紫衣青年、冷峻",
        "docId": "plot.xianni-ch31-36-xueshui-jiaoyi",
        "seq": 31
      }
    ],
    "标志特征": [
      {
        "value": "气息极危险，远超孙大柱、张虎",
        "docId": "plot.xianni-ch31-36-xueshui-jiaoyi",
        "seq": 31
      }
    ],
    "性格": [
      {
        "value": "心机深沉、伪作亲和",
        "docId": "plot.xianni-ch31-36-xueshui-jiaoyi",
        "seq": 31
      }
    ]
  },
  "firstSeq": 31,
  "attrProvenance": {
    "身份": {
      "asOf": null,
      "docId": "plot.xianni-ch31-36-xueshui-jiaoyi",
      "dated": false,
      "seq": 31
    },
    "称号": {
      "asOf": null,
      "docId": "plot.xianni-ch31-36-xueshui-jiaoyi",
      "dated": false,
      "seq": 31
    },
    "小阶段": {
      "asOf": null,
      "docId": "plot.xianni-ch31-36-xueshui-jiaoyi",
      "dated": false,
      "seq": 31,
      "note": "据弟子所述去年比试最强；本章现身气息远超寻常弟子，疑深藏修为"
    },
    "外貌": {
      "asOf": null,
      "docId": "plot.xianni-ch31-36-xueshui-jiaoyi",
      "dated": false,
      "seq": 31
    },
    "标志特征": {
      "asOf": null,
      "docId": "plot.xianni-ch31-36-xueshui-jiaoyi",
      "dated": false,
      "seq": 31
    },
    "性格": {
      "asOf": null,
      "docId": "plot.xianni-ch31-36-xueshui-jiaoyi",
      "dated": false,
      "seq": 31
    }
  },
  "contested": false,
  "contradictions": {},
  "docs": [
    "plot.xianni-ch31-36-xueshui-jiaoyi",
    "plot.xianni-ch37-42-sinian-guangban"
  ],
  "updatedAt": "2026-06-22T12:17:35.999Z"
}
