{
  "id": "ent.person.x-5ade3343",
  "type": "person",
  "name": "即墨老人",
  "aliases": [
    "即墨"
  ],
  "summary": "散修，传闻已达结丹期，最护短，白展师尊，将追查白展之死。",
  "attributes": {
    "身份": "散修",
    "小阶段": "结丹期",
    "性格": "护短",
    "标志特征": "控制门下弟子的秘术、推算秘术",
    "阵营": "赵国修真界"
  },
  "observations": {
    "身份": [
      {
        "value": "散修",
        "docId": "plot.xianni-ch61-66-strange-sword-baizhan",
        "seq": 61
      }
    ],
    "小阶段": [
      {
        "value": "结丹期",
        "docId": "plot.xianni-ch61-66-strange-sword-baizhan",
        "seq": 61
      }
    ],
    "性格": [
      {
        "value": "护短",
        "docId": "plot.xianni-ch61-66-strange-sword-baizhan",
        "seq": 61
      }
    ],
    "标志特征": [
      {
        "value": "控制门下弟子的秘术",
        "docId": "plot.xianni-ch67-71-tengli-chase-lanxianteng",
        "seq": 67
      },
      {
        "value": "推算秘术",
        "docId": "plot.xianni-ch67-71-tengli-chase-lanxianteng",
        "seq": 67
      }
    ],
    "阵营": [
      {
        "value": "王林敌对",
        "docId": "plot.xianni-ch117-wanglin-death",
        "seq": 102,
        "note": "藤化元单方所述"
      },
      {
        "value": "王林必杀名单",
        "docId": "plot.xianni-ch186-187-two-hundred-years-silence",
        "seq": 186
      },
      {
        "value": "赵国修真界",
        "docId": "plot.xianni-ch206-guixi-yuanying-qiusiping",
        "seq": 190
      }
    ]
  },
  "firstSeq": 61,
  "attrProvenance": {
    "身份": {
      "asOf": null,
      "docId": "plot.xianni-ch61-66-strange-sword-baizhan",
      "dated": false,
      "seq": 61
    },
    "小阶段": {
      "asOf": null,
      "docId": "plot.xianni-ch61-66-strange-sword-baizhan",
      "dated": false,
      "seq": 61
    },
    "性格": {
      "asOf": null,
      "docId": "plot.xianni-ch61-66-strange-sword-baizhan",
      "dated": false,
      "seq": 61
    },
    "标志特征": {
      "asOf": null,
      "docId": "plot.xianni-ch67-71-tengli-chase-lanxianteng",
      "dated": false,
      "seq": 67
    },
    "阵营": {
      "asOf": null,
      "docId": "plot.xianni-ch206-guixi-yuanying-qiusiping",
      "dated": false,
      "seq": 190
    }
  },
  "contested": false,
  "contradictions": {},
  "docs": [
    "plot.xianni-ch61-66-strange-sword-baizhan",
    "plot.xianni-ch67-71-tengli-chase-lanxianteng",
    "plot.xianni-ch117-wanglin-death",
    "plot.xianni-ch186-187-two-hundred-years-silence",
    "plot.xianni-ch206-guixi-yuanying-qiusiping"
  ],
  "updatedAt": "2026-07-07T12:09:47.092Z"
}
