{
  "id": "ent.pill.x-0297150f",
  "type": "pill",
  "name": "疗伤丹",
  "aliases": [],
  "summary": "李慕婉所赠药物之一，王林重伤后服下一粒疗伤。",
  "attributes": {
    "功效": "疗伤",
    "炼制者": "（李慕婉所赠）"
  },
  "observations": {
    "功效": [
      {
        "value": "疗伤",
        "docId": "plot.xianni-142-146-qimei-rongyan-wuqi-huahai",
        "seq": 142
      }
    ],
    "炼制者": [
      {
        "value": "（李慕婉所赠）",
        "docId": "plot.xianni-142-146-qimei-rongyan-wuqi-huahai",
        "seq": 142
      }
    ]
  },
  "firstSeq": 142,
  "attrProvenance": {
    "功效": {
      "asOf": null,
      "docId": "plot.xianni-142-146-qimei-rongyan-wuqi-huahai",
      "dated": false,
      "seq": 142
    },
    "炼制者": {
      "asOf": null,
      "docId": "plot.xianni-142-146-qimei-rongyan-wuqi-huahai",
      "dated": false,
      "seq": 142
    }
  },
  "contested": false,
  "contradictions": {},
  "docs": [
    "plot.xianni-142-146-qimei-rongyan-wuqi-huahai"
  ],
  "updatedAt": "2026-07-06T15:09:57.861Z"
}
