{
  "id": "ent.spell.x-58d186a4",
  "type": "spell",
  "name": "水遁术",
  "aliases": [],
  "summary": "六欲魔君五百年前得宝所施，效同汪清越的土行舟，助其度过冰川之地。",
  "attributes": {
    "类型": "遁术"
  },
  "observations": {
    "类型": [
      {
        "value": "遁术",
        "docId": "plot.xianni-ch179-180-jinshan-study-restrictions",
        "seq": 164
      }
    ]
  },
  "firstSeq": 164,
  "attrProvenance": {
    "类型": {
      "asOf": null,
      "docId": "plot.xianni-ch179-180-jinshan-study-restrictions",
      "dated": false,
      "seq": 164
    }
  },
  "contested": false,
  "contradictions": {},
  "docs": [
    "plot.xianni-ch179-180-jinshan-study-restrictions"
  ],
  "updatedAt": "2026-07-07T02:42:08.963Z"
}
