{
  "id": "ent.passage.x-053ecad2",
  "type": "passage",
  "name": "传送阵",
  "aliases": [],
  "summary": "域外战场内可离开的传送阵，即将开启；若战场彻底坍塌恐无法开启。",
  "attributes": {
    "类型": "传送阵"
  },
  "observations": {
    "类型": [
      {
        "value": "传送阵",
        "docId": "plot.xianni-ch106-110-tomb-jailer-devourer-wanglin-possess-maliang",
        "seq": 106
      }
    ]
  },
  "firstSeq": 106,
  "attrProvenance": {
    "类型": {
      "asOf": null,
      "docId": "plot.xianni-ch106-110-tomb-jailer-devourer-wanglin-possess-maliang",
      "dated": false,
      "seq": 106
    }
  },
  "contested": false,
  "contradictions": {},
  "docs": [
    "plot.xianni-ch106-110-tomb-jailer-devourer-wanglin-possess-maliang"
  ],
  "updatedAt": "2026-07-05T04:23:08.034Z"
}
